tacz/constants.py
tacz/main.py
tacz/config/__init__.py
tacz/config/setup.py
tacz/llms/__init__.py
tacz/llms/provider_factory.py
tacz/llms/types.py
tacz/llms/providers/__init__.py
tacz/llms/providers/ollama_provider.py
tacz/tools/collect_commands.py
tacz/tools/edit_commands.py
tacz/utils/__init__.py
tacz/utils/command_db.py
tacz/utils/os_detect.py
tacz/utils/safety.py
tacz-1.0.2.dist-info/METADATA
tacz-1.0.2.dist-info/WHEEL
tacz-1.0.2.dist-info/entry_points.txt
tacz-1.0.2.dist-info/top_level.txt
tacz-1.0.2.dist-info/RECORD
