Metadata-Version: 2.4
Name: tacz
Version: 1.0.2
Summary: Local command assistant using Ollama
Project-URL: Repository, https://github.com/duriantaco/tacz
Classifier: Programming Language :: Python :: 3
Classifier: Programming Language :: Python :: 3.9
Classifier: Programming Language :: Python :: 3.10
Classifier: Programming Language :: Python :: 3.11
Classifier: Programming Language :: Python :: 3.12
Classifier: License :: OSI Approved :: Apache Software License
Classifier: Operating System :: OS Independent
Requires-Python: >=3.9
Requires-Dist: pydantic>=2.10.6
Requires-Dist: pyperclip>=1.9.0
Requires-Dist: python-dotenv>=1.0.1
Requires-Dist: questionary>=2.1.0
Requires-Dist: rich>=13.9.4
Requires-Dist: requests>=2.31.0
Requires-Dist: sentence-transformers>=2.7.0
Requires-Dist: torch<3.0,>=2.2.0
Requires-Dist: numpy<2.0,>=1.26
